sql_composer/__init__.py
sql_composer/db_conditions.py
sql_composer/db_metadata.py
sql_composer/db_models.py
sql_composer/sql_composer.py
sql_composer/sql_translator.py
sql_composer/pg/__init__.py
sql_composer/pg/pg_data_types.py
sql_composer/pg/pg_filter_op.py
sql_composer/pg/pg_translator.py
shiba_sql_composer-0.1.0.dist-info/METADATA
shiba_sql_composer-0.1.0.dist-info/WHEEL
shiba_sql_composer-0.1.0.dist-info/licenses/LICENSE
shiba_sql_composer-0.1.0.dist-info/RECORD
