Metadata-Version: 2.4
Name: shiba-sql-composer
Version: 0.1.0
Summary: A type-safe SQL query builder and composer for Python
Project-URL: Homepage, https://github.com/leeaaron629/sql-composer
Project-URL: Repository, https://github.com/leeaaron629/sql-composer
Project-URL: Issues, https://github.com/leeaaron629/sql-composer/issues
Author-email: Aaron Lee <leeaaron326@gmail.com>
License: Apache-2.0
License-File: LICENSE
Keywords: database,postgresql,query-builder,sql,type-safe
Classifier: Development Status :: 3 - Alpha
Classifier: Intended Audience :: Developers
Classifier: License :: OSI Approved :: Apache Software License
Classifier: Operating System :: OS Independent
Classifier: Programming Language :: Python :: 3
Classifier: Programming Language :: Python :: 3.11
Classifier: Programming Language :: Python :: 3.12
Classifier: Programming Language :: Python :: 3.13
Classifier: Topic :: Database
Classifier: Topic :: Software Development :: Libraries :: Python Modules
Classifier: Typing :: Typed
Requires-Python: >=3.11
Requires-Dist: psycopg2-binary>=2.9.0
Requires-Dist: python-dotenv>=1.0.0
Provides-Extra: dev
Requires-Dist: pyright>=1.1.407; extra == 'dev'
Requires-Dist: pytest-cov>=4.0.0; extra == 'dev'
Requires-Dist: pytest>=9.0.1; extra == 'dev'
Requires-Dist: ruff>=0.14.8; extra == 'dev'
